mindai/__init__.py
mindai/mindai.py
mindai-2023.1.3.dist-info/LICENSE
mindai-2023.1.3.dist-info/METADATA
mindai-2023.1.3.dist-info/WHEEL
mindai-2023.1.3.dist-info/top_level.txt
mindai-2023.1.3.dist-info/RECORD
