Metadata-Version: 2.1
Name: mindai
Version: 2023.1.3
Summary: list of tools using ai.
Home-page: 
Author: ReBack
Author-email: 
Project-URL: Bug Tracker, https://github.com/pypa/sampleproject/issues
Keywords: ai,openai
Classifier: Development Status :: 1 - Planning
Classifier: Intended Audience :: Developers
Classifier: Programming Language :: Python :: 3
License-File: LICENSE
Requires-Dist: requests
